{
    "frontLeftDriveMotorPort": 5,
    "frontRightDriveMotorPort": 3,
    "backLeftDriveMotorPort": 7,
    "backRightDriveMotorPort": 1,

    "frontLeftTurningMotorPort": 6,
    "frontRightTurningMotorPort": 4,
    "backLeftTurningMotorPort": 8,
    "backRightTurningMotorPort": 2,

    "frontLeftTurningEncoderPort": 0,
    "frontRightTurningEncoderPort": 3,
    "backLeftTurningEncoderPort": 1,
    "backRightTurningEncoderPort": 2,

    "frontLeftOffset": 6.0546,
    "frontRightOffset": 6.2060,
    "backLeftOffset": 0.6414,
    "backRightOffset": 5.6427,
    
    "extraShuffleBoardToggle": false,
    "limelighturl": "http://10.43.29.11:5800",
    "usesPhotonVision": false,
    "rollDirection": 1
}